tangled_game_engine/__init__.py
tangled_game_engine/tangled_game/__init__.py
tangled_game_engine/tangled_game/game.py
tangled_game_engine/tangled_game/game_graphs.py
tangled_game_engine/tangled_game/game_types.py
tangled_game_engine-2.2.0.dist-info/METADATA
tangled_game_engine-2.2.0.dist-info/WHEEL
tangled_game_engine-2.2.0.dist-info/entry_points.txt
tangled_game_engine-2.2.0.dist-info/RECORD
