Metadata-Version: 2.1
Name: tangled-game-engine
Version: 2.2.0
Summary: A package for the Tangled game engine and support classes.
Home-page: https://github.com/snowdropquantum/tangled-game-package
Author: Erik Kiss
Author-email: erik@snowdropquantum.com
Requires-Python: >=3.8,<4.0
Classifier: Programming Language :: Python :: 3
Classifier: Programming Language :: Python :: 3.8
Classifier: Programming Language :: Python :: 3.9
Classifier: Programming Language :: Python :: 3.10
Classifier: Programming Language :: Python :: 3.11
Classifier: Programming Language :: Python :: 3.12
Classifier: Programming Language :: Python :: 3.13
Requires-Dist: pydantic (>=2.0.0)
Requires-Dist: python-dateutil (>=2.5.3)
Requires-Dist: requests (>=2.31.0)
Requires-Dist: typing-extensions (>=4.7.1)
Requires-Dist: urllib3 (>=1.25.3,<2.1.0)
Project-URL: repository, https://github.com/snowdropquantum/tangled-game-package
